rompy_binary_datasources/__init__.py
rompy_binary_datasources/rompy_binary_datasources.py
rompy_binary_datasources/source.py
rompy_binary_datasources-0.1.0.dist-info/licenses/AUTHORS.rst
rompy_binary_datasources-0.1.0.dist-info/licenses/LICENSE
rompy_binary_datasources-0.1.0.dist-info/METADATA
rompy_binary_datasources-0.1.0.dist-info/WHEEL
rompy_binary_datasources-0.1.0.dist-info/entry_points.txt
rompy_binary_datasources-0.1.0.dist-info/top_level.txt
rompy_binary_datasources-0.1.0.dist-info/RECORD
