Metadata-Version: 2.4
Name: rompy_binary_datasources
Version: 0.1.0
Summary: Binary datasource for rompy
Author-email: Rompy Developers <developers@oceanum.science>
Maintainer-email: Rompy Developers <developers@oceanum.science>
License: BSD license
Project-URL: bugs, https://github.com/rompy-py/rompy_binary_datasources/issues
Project-URL: changelog, https://github.com/rompy-py/rompy_binary_datasources/blob/master/changelog.md
Project-URL: homepage, https://github.com/rompy-py/rompy_binary_datasources
License-File: LICENSE
License-File: AUTHORS.rst
Requires-Dist: rompy
Requires-Dist: pandas
Requires-Dist: xarray
Provides-Extra: dev
Requires-Dist: coverage; extra == "dev"
Requires-Dist: mypy; extra == "dev"
Requires-Dist: pytest; extra == "dev"
Requires-Dist: ruff; extra == "dev"
Dynamic: license-file
